api_for_iot_module/__init__.py
api_for_iot_module/api_for_iot_module.py
api_for_iot_module/cli.py
tests/__init__.py
tests/test_api_for_iot_module.py
api_for_iot_module-1.0.1.dist-info/AUTHORS.rst
api_for_iot_module-1.0.1.dist-info/LICENSE
api_for_iot_module-1.0.1.dist-info/METADATA
api_for_iot_module-1.0.1.dist-info/WHEEL
api_for_iot_module-1.0.1.dist-info/entry_points.txt
api_for_iot_module-1.0.1.dist-info/top_level.txt
api_for_iot_module-1.0.1.dist-info/RECORD
