Metadata-Version: 2.1
Name: api-for-iot-module
Version: 1.0.1
Summary: API for IoT Module contains functions to be used for implementing a API for a camera module 
Home-page: https://github.com/ChezzyBoi/api_for_iot_module
Author: Cheslyn Williams
Author-email: cheslynwilliams318@gmail.com
License: MIT license
Keywords: api_for_iot_module
Platform: UNKNOWN
Classifier: Development Status :: 2 - Pre-Alpha
Classifier: Intended Audience :: Developers
Classifier: License :: OSI Approved :: MIT License
Classifier: Natural Language :: English
Classifier: Programming Language :: Python :: 3
Classifier: Programming Language :: Python :: 3.5
Classifier: Programming Language :: Python :: 3.6
Classifier: Programming Language :: Python :: 3.7
Classifier: Programming Language :: Python :: 3.8
Requires-Python: >=3.5
Requires-Dist: Click (>=7.0)
